CHANGES.rst
CONTRIBUTORS.rst
MANIFEST.in
README.rst
setup.cfg
setup.py
docs/LICENSE.GPL
docs/LICENSE.rst
docs/index.rst
src/collective/__init__.py
src/collective.tiles.iframembed.egg-info/PKG-INFO
src/collective.tiles.iframembed.egg-info/SOURCES.txt
src/collective.tiles.iframembed.egg-info/dependency_links.txt
src/collective.tiles.iframembed.egg-info/entry_points.txt
src/collective.tiles.iframembed.egg-info/namespace_packages.txt
src/collective.tiles.iframembed.egg-info/not-zip-safe
src/collective.tiles.iframembed.egg-info/requires.txt
src/collective.tiles.iframembed.egg-info/top_level.txt
src/collective/tiles/__init__.py
src/collective/tiles/iframembed/__init__.py
src/collective/tiles/iframembed/configure.zcml
src/collective/tiles/iframembed/interfaces.py
src/collective/tiles/iframembed/setuphandlers.py
src/collective/tiles/iframembed/testing.py
src/collective/tiles/iframembed/tile.pt
src/collective/tiles/iframembed/tile.py
src/collective/tiles/iframembed/upgrades.py
src/collective/tiles/iframembed/upgrades.zcml
src/collective/tiles/iframembed/browser/__init__.py
src/collective/tiles/iframembed/browser/configure.zcml
src/collective/tiles/iframembed/browser/controlpanel.py
src/collective/tiles/iframembed/browser/overrides/.gitkeep
src/collective/tiles/iframembed/browser/static/.gitkeep
src/collective/tiles/iframembed/locales/collective.tiles.iframembed.pot
src/collective/tiles/iframembed/locales/update.sh
src/collective/tiles/iframembed/locales/it/LC_MESSAGES/collective.tiles.iframembed.mo
src/collective/tiles/iframembed/locales/it/LC_MESSAGES/collective.tiles.iframembed.po
src/collective/tiles/iframembed/profiles/cleanup/collectivetilesiframembed_cleanup.txt
src/collective/tiles/iframembed/profiles/cleanup/registry.xml
src/collective/tiles/iframembed/profiles/default/browserlayer.xml
src/collective/tiles/iframembed/profiles/default/collectivetilesiframembed_default.txt
src/collective/tiles/iframembed/profiles/default/controlpanel.xml
src/collective/tiles/iframembed/profiles/default/metadata.xml
src/collective/tiles/iframembed/profiles/default/registry.xml
src/collective/tiles/iframembed/profiles/mosaic_support/registry.xml
src/collective/tiles/iframembed/profiles/uninstall/browserlayer.xml
src/collective/tiles/iframembed/profiles/uninstall/collectivetilesiframembed_uninstall.txt
src/collective/tiles/iframembed/profiles/uninstall/controlpanel.xml
